ruins/__init__.py
ruins/main.py
ruins-0.0.2.dist-info/METADATA
ruins-0.0.2.dist-info/WHEEL
ruins-0.0.2.dist-info/entry_points.txt
ruins-0.0.2.dist-info/top_level.txt
ruins-0.0.2.dist-info/RECORD
