Metadata-Version: 2.1
Name: ruins
Version: 0.0.2
Summary: Static page generator
Home-page: UNKNOWN
Author: Hiroki Kiyohara
Author-email: hirokiky@gmail.com
License: MIT
Platform: UNKNOWN
Requires-Dist: MarkupSafe==2.0.1
Requires-Dist: jinja2==2.11.1
Requires-Dist: libsass==0.19.4
